sunbay_nexus_sdk/__init__.py
sunbay_nexus_sdk/client.py
sunbay_nexus_sdk/constants/__init__.py
sunbay_nexus_sdk/constants/api_constants.py
sunbay_nexus_sdk/enums/__init__.py
sunbay_nexus_sdk/exceptions/__init__.py
sunbay_nexus_sdk/http/__init__.py
sunbay_nexus_sdk/models/base.py
sunbay_nexus_sdk/models/common.py
sunbay_nexus_sdk/models/request.py
sunbay_nexus_sdk/models/response.py
sunbay_nexus_sdk/utils/__init__.py
sunbay_nexus_sdk/utils/id_generator.py
sunbay_nexus_sdk-1.0.9.dist-info/METADATA
sunbay_nexus_sdk-1.0.9.dist-info/WHEEL
sunbay_nexus_sdk-1.0.9.dist-info/top_level.txt
sunbay_nexus_sdk-1.0.9.dist-info/RECORD
