Metadata-Version: 2.4
Name: sunbay-nexus-sdk
Version: 1.0.9
Summary: Official Sunbay Nexus Python SDK
Author-email: Sunbay <support@sunbay.example>
License: MIT
Project-URL: Homepage, https://open.sunbay.us
Project-URL: Source, https://example.com/sunbay-nexus-sdk-python
Classifier: Programming Language :: Python :: 3
Classifier: Programming Language :: Python :: 3 :: Only
Classifier: Programming Language :: Python :: 3.7
Classifier: Programming Language :: Python :: 3.8
Classifier: Programming Language :: Python :: 3.9
Classifier: Programming Language :: Python :: 3.10
Classifier: Programming Language :: Python :: 3.11
Classifier: Programming Language :: Python :: 3.12
Classifier: License :: OSI Approved :: MIT License
Classifier: Intended Audience :: Developers
Classifier: Topic :: Software Development :: Libraries
Requires-Python: >=3.7
Requires-Dist: requests<3.0,>=2.28
